tiktok_captcha_solver/__init__.py
tiktok_captcha_solver/api.py
tiktok_captcha_solver/asyncplaywrightsolver.py
tiktok_captcha_solver/asyncsolver.py
tiktok_captcha_solver/captchatype.py
tiktok_captcha_solver/download_crx.py
tiktok_captcha_solver/downloader.py
tiktok_captcha_solver/geometry.py
tiktok_captcha_solver/launcher.py
tiktok_captcha_solver/models.py
tiktok_captcha_solver/nodriversolver.py
tiktok_captcha_solver/playwrightsolver.py
tiktok_captcha_solver/selectors.py
tiktok_captcha_solver/seleniumsolver.py
tiktok_captcha_solver/solver.py
tiktok_captcha_solver/tests/__init__.py
tiktok_captcha_solver/tests/test_api.py
tiktok_captcha_solver/tests/test_asyncplaywrightsolver.py
tiktok_captcha_solver/tests/test_download_crx.py
tiktok_captcha_solver/tests/test_downloader.py
tiktok_captcha_solver/tests/test_launcher.py
tiktok_captcha_solver/tests/test_playwrightsolver.py
tiktok_captcha_solver/tests/test_seleniumsolver.py
tiktok_captcha_solver-0.8.3.dist-info/METADATA
tiktok_captcha_solver-0.8.3.dist-info/WHEEL
tiktok_captcha_solver-0.8.3.dist-info/top_level.txt
tiktok_captcha_solver-0.8.3.dist-info/RECORD
