Metadata-Version: 2.1
Name: tiktok-captcha-solver
Version: 0.8.3
Summary: This package integrates with Selenium or Playwright to solve any TikTok captcha in one line of code.
Author-email: Toughdata LLC <greg@toughdata.net>
Project-URL: Homepage, https://www.sadcaptcha.com
Project-URL: Source, https://github.com/gbiz123/tiktok-captcha-solver/
Keywords: tiktok,captcha,solver,selenium,rotate,puzzle,3d
Classifier: Intended Audience :: Developers
Classifier: Topic :: Software Development :: Build Tools
Classifier: Programming Language :: Python :: 3.10
Classifier: Programming Language :: Python :: 3.11
Classifier: Programming Language :: Python :: 3.12
Classifier: Programming Language :: Python :: 3 :: Only
Requires-Python: >=3.10
Requires-Dist: selenium
Requires-Dist: webdriver-manager
Requires-Dist: pydantic
Requires-Dist: requests
Requires-Dist: pytest
Requires-Dist: pytest-asyncio
Requires-Dist: playwright
Requires-Dist: playwright-stealth
Requires-Dist: undetected-chromedriver
Requires-Dist: setuptools
